flow_exporter/__init__.py
flow_exporter/__main__.py
flow_exporter/main.py
flow_exporter-0.1.1.dist-info/METADATA
flow_exporter-0.1.1.dist-info/WHEEL
flow_exporter-0.1.1.dist-info/entry_points.txt
flow_exporter-0.1.1.dist-info/top_level.txt
flow_exporter-0.1.1.dist-info/RECORD
