Metadata-Version: 2.4
Name: flow_exporter
Version: 0.1.1
Summary: Экспорт и импорт графовых JSON-проектов Langflow
Author-email: Obraztsov Oleg Aleksandrovich <olegrasputina@gmail.com>
License: MIT
Keywords: langflow,export,import,graph,workflow
Requires-Python: >=3.9
Requires-Dist: pytest
